<annotation>
  <folder>VOC2012</folder>
  <filename>coreless_battery00000094.jpg</filename>
  <size>
    <width>1040</width>
    <height>2000</height>
    <depth>3</depth>
  </size>
  <object>
    <name>undefined</name>
    <difficult>0</difficult>
    <bndbox>
      <xmin>443</xmin>
      <ymin>734</ymin>
      <xmax>569</xmax>
      <ymax>819</ymax>
    </bndbox>
  </object>
  <object>
    <name>coreless</name>
    <difficult>0</difficult>
    <bndbox>
      <xmin>443</xmin>
      <ymin>734</ymin>
      <xmax>569</xmax>
      <ymax>819</ymax>
    </bndbox>
  </object>
</annotation>
